calculadora/__init__.py
calculadora/calculadora.py
afoone_calculadora-0.1.dist-info/LICENSE.txt
afoone_calculadora-0.1.dist-info/METADATA
afoone_calculadora-0.1.dist-info/WHEEL
afoone_calculadora-0.1.dist-info/top_level.txt
afoone_calculadora-0.1.dist-info/RECORD
